energyplus_diffs/__init__.py
energyplus_diffs/__main__.py
energyplus_diffs/cli.py
energyplus_diffs/compress.py
energyplus_diffs/plot_vars.py
energyplus_diff_analysis-0.2.dist-info/LICENSE
energyplus_diff_analysis-0.2.dist-info/METADATA
energyplus_diff_analysis-0.2.dist-info/WHEEL
energyplus_diff_analysis-0.2.dist-info/entry_points.txt
energyplus_diff_analysis-0.2.dist-info/top_level.txt
energyplus_diff_analysis-0.2.dist-info/RECORD
