Metadata-Version: 2.1
Name: energyplus-diff-analysis
Version: 0.2
Summary: A tool used for plotting and comparing separate EnergyPlus output CSV files.
Home-page: https://github.com/mitchute/energyplus-diff-analysis
Author: Matt Mitchell
Author-email: mitchute@gmail.com
License: MIT
Platform: UNKNOWN
Requires-Dist: click (>=8.1.3)
Requires-Dist: matplotlib (>=3.7.0)
Requires-Dist: pandas (>=1.5.3)
